shortesttrack/__init__.py
shortesttrack/constants.py
shortesttrack/utils.py
shortesttrack/client/__init__.py
shortesttrack/client/access_token.py
shortesttrack/client/asec_helper.py
shortesttrack/client/iss_connector.py
shortesttrack/client/issc_helper.py
shortesttrack/client/performance_helper.py
shortesttrack/client/sec_helper.py
shortesttrack/conf/__init__.py
shortesttrack/conf/lib_conf.py
shortesttrack/conf/library.py
shortesttrack/library/__init__.py
shortesttrack/library/analytic_script_configuration.py
shortesttrack/library/script_configuration.py
shortesttrack/library/st_library.py
shortesttrack/library/batch/__init__.py
shortesttrack/library/batch/base_solver.py
shortesttrack/library/iterative/__init__.py
shortesttrack/library/iterative/mixins.py
shortesttrack/library/iterative/async/__init__.py
shortesttrack/library/iterative/async/base_solver.py
shortesttrack/library/iterative/sync/__init__.py
shortesttrack/library/iterative/sync/base_solver.py
shortesttrack/models/__init__.py
shortesttrack/models/analytic_script_configuration.py
shortesttrack/models/iterative_script_configuration.py
shortesttrack/models/matrix.py
shortesttrack/models/performance.py
shortesttrack/models/script_configuration.py
shortesttrack/models/base/__init__.py
shortesttrack/models/base/model.py
shortesttrack_sdk-1.4.1.dist-info/LICENSE
shortesttrack_sdk-1.4.1.dist-info/METADATA
shortesttrack_sdk-1.4.1.dist-info/WHEEL
shortesttrack_sdk-1.4.1.dist-info/top_level.txt
shortesttrack_sdk-1.4.1.dist-info/RECORD
